BioModTool/__init__.py
BioModTool/calculate.py
BioModTool/load.py
BioModTool/main_add_biomass_objective_function.py
BioModTool/remove_biomass_objective_function.py
BioModTool/save.py
BioModTool/test.py
BioModTool/update.py
BioModTool-1.0.0.dist-info/LICENSE.md
BioModTool-1.0.0.dist-info/METADATA
BioModTool-1.0.0.dist-info/WHEEL
BioModTool-1.0.0.dist-info/top_level.txt
BioModTool-1.0.0.dist-info/RECORD
