Metadata-Version: 2.1
Name: BioModTool
Version: 1.0.0
Summary: Package to generate biomass objective functions to update genome-scale metabolic models.
Home-page: UNKNOWN
License: LGPL
Platform: UNKNOWN
Requires-Dist: cobra
Requires-Dist: numpy
Requires-Dist: pandas
Requires-Dist: openpyxl
